README.rst
setup.py
tieba_to_epub/__init__.py
tieba_to_epub/main.py
tieba_to_epub/nodes.py
tieba_to_epub/parsers.py
tieba_to_epub.egg-info/PKG-INFO
tieba_to_epub.egg-info/SOURCES.txt
tieba_to_epub.egg-info/dependency_links.txt
tieba_to_epub.egg-info/entry_points.txt
tieba_to_epub.egg-info/requires.txt
tieba_to_epub.egg-info/top_level.txt
tieba_to_epub/builders/__init__.py
tieba_to_epub/builders/base.py
tieba_to_epub/builders/epub.py
tieba_to_epub/builders/html.py
tieba_to_epub/templates/chapter.html
tieba_to_epub/templates/macros.html
tieba_to_epub/templates/template.html