Metadata-Version: 1.0
Name: tieba-to-epub
Version: 0.0.6
Summary: convert baidu tieba post to epub
Home-page: https://github.com/lexdene/tieba-post-to-epub
Author: Elephant Liu
Author-email: elephant_liu@mail.dlut.edu.cn
License: GPLv3
Platform: any
